{
    "question": "Are you currently employed as a professor at RMIT?",
    "answer": "Yes",
    "mouseMovements": [
        [
            527,
            582
        ],
        [
            528,
            581
        ],
        [
            528,
            580
        ],
        [
            528,
            579
        ],
        [
            528,
            578
        ],
        [
            529,
            578
        ],
        [
            529,
            577
        ],
        [
            529,
            575
        ],
        [
            530,
            574
        ],
        [
            532,
            571
        ],
        [
            534,
            568
        ],
        [
            536,
            566
        ],
        [
            537,
            563
        ],
        [
            540,
            559
        ],
        [
            543,
            552
        ],
        [
            549,
            545
        ],
        [
            556,
            535
        ],
        [
            565,
            522
        ],
        [
            581,
            499
        ],
        [
            600,
            470
        ],
        [
            623,
            430
        ],
        [
            644,
            397
        ],
        [
            666,
            365
        ],
        [
            685,
            338
        ],
        [
            702,
            311
        ],
        [
            718,
            286
        ],
        [
            730,
            265
        ],
        [
            738,
            250
        ],
        [
            744,
            237
        ],
        [
            749,
            227
        ],
        [
            753,
            219
        ],
        [
            756,
            211
        ],
        [
            758,
            206
        ],
        [
            760,
            201
        ],
        [
            762,
            199
        ],
        [
            764,
            195
        ],
        [
            765,
            191
        ],
        [
            767,
            188
        ],
        [
            768,
            186
        ],
        [
            768,
            185
        ],
        [
            768,
            184
        ],
        [
            768,
            183
        ],
        [
            764,
            185
        ],
        [
            760,
            191
        ],
        [
            756,
            195
        ],
        [
            752,
            200
        ],
        [
            749,
            204
        ],
        [
            747,
            206
        ],
        [
            744,
            209
        ],
        [
            741,
            211
        ],
        [
            739,
            211
        ],
        [
            737,
            213
        ],
        [
            736,
            213
        ],
        [
            736,
            214
        ],
        [
            734,
            215
        ],
        [
            732,
            215
        ],
        [
            731,
            216
        ],
        [
            730,
            216
        ],
        [
            729,
            217
        ],
        [
            728,
            217
        ],
        [
            728,
            218
        ],
        [
            726,
            219
        ],
        [
            725,
            219
        ],
        [
            724,
            219
        ],
        [
            723,
            221
        ],
        [
            721,
            222
        ],
        [
            720,
            223
        ],
        [
            719,
            224
        ],
        [
            717,
            226
        ],
        [
            714,
            229
        ],
        [
            712,
            231
        ],
        [
            711,
            232
        ],
        [
            710,
            233
        ],
        [
            710,
            234
        ],
        [
            708,
            235
        ],
        [
            707,
            237
        ],
        [
            705,
            238
        ],
        [
            704,
            239
        ],
        [
            703,
            241
        ],
        [
            701,
            243
        ],
        [
            700,
            244
        ],
        [
            699,
            245
        ]
    ],
    "timestamps": [
        0.009,
        0.058,
        0.077,
        0.085,
        0.123,
        0.144,
        0.161,
        0.212,
        0.221,
        0.228,
        0.244,
        0.251,
        0.26,
        0.266,
        0.275,
        0.281,
        0.289,
        0.298,
        0.305,
        0.314,
        0.32,
        0.328,
        0.336,
        0.343,
        0.351,
        0.36,
        0.368,
        0.376,
        0.383,
        0.397,
        0.404,
        0.411,
        0.418,
        0.425,
        0.432,
        0.439,
        0.446,
        0.453,
        0.461,
        0.469,
        0.477,
        0.485,
        0.644,
        0.652,
        0.659,
        0.666,
        0.674,
        0.681,
        0.69,
        0.697,
        0.706,
        0.714,
        0.729,
        0.793,
        0.801,
        0.811,
        0.817,
        0.825,
        0.84,
        0.861,
        0.868,
        0.881,
        0.895,
        0.903,
        0.911,
        0.916,
        0.923,
        0.93,
        0.937,
        0.951,
        0.958,
        0.982,
        0.989,
        0.997,
        1.005,
        1.013,
        1.02,
        1.028,
        1.041,
        1.048,
        1.055,
        1.062
    ],
    "accelerations": [
        0,
        -1779785.61448534,
        1251.0567197077958,
        9046.052631578947,
        -2596.9529085872573,
        1014.4408640649237,
        659.0871642774758,
        -384.46751249519406,
        13102.128221018607,
        51134.84476771935,
        -18108.237432575832,
        25530.580443483574,
        -5855.203706414557,
        80328.19147836334,
        1429.297603258129,
        115065.62185324855,
        -1346.4113644294002,
        25666.83003878375,
        320818.4693068048,
        -16704.694079644065,
        639662.2282154913,
        -350097.4407671957,
        -4409.980520635713,
        -19667.462851427445,
        -91023.21079886923,
        -76700.39680446821,
        -34326.72581672301,
        -112293.3319514945,
        -11370.998708645857,
        -89057.66448496815,
        68451.06053570785,
        -8168.7380547271005,
        -64466.10077924544,
        0,
        -52178.32004874109,
        33545.07816843651,
        -7123.067946569774,
        -10562.333676605542,
        -29446.28205627987,
        -19313.562148434215,
        0,
        0,
        -609.2664073810538,
        109157.64720494811,
        -13323.68331774694,
        15229.999753887098,
        -36216.504239872294,
        -31562.711739873666,
        7482.611441127486,
        6239.176120954426,
        -32539.614601721165,
        16416.396046381444,
        -19125.78159510714,
        -797.5260416666667,
        32985.43714843421,
        -7950.849718747372,
        5950.376732585975,
        -13837.78254943948,
        -2047.9397227862441,
        -2221.9931685313677,
        13605.442176870749,
        2242.160475484809,
        -7184.046972133853,
        6696.428571428571,
        19313.562148434215,
        33541.019662496845,
        -35026.15522707368,
        0,
        28861.501272920308,
        -7215.375318230079,
        14430.750636460158,
        -14380.64386341689,
        20443.563401651885,
        -9628.81361380527,
        19313.562148434215,
        0,
        5704.255044642317,
        -17832.698400416633,
        -367.0358660147315,
        33150.82696891985,
        -28861.501272920308,
        0
    ],
    "jerks": [
        0,
        -1000000,
        1000000,
        0,
        -1000000,
        227409.63025135046,
        59777.41610403519,
        -19334.514950244877,
        0,
        0,
        -1000000,
        0,
        0,
        0,
        0,
        0,
        0,
        0,
        0,
        0,
        0,
        0,
        0,
        0,
        0,
        0,
        0,
        0,
        0,
        -1000000,
        0,
        0,
        0,
        0,
        0,
        0,
        0,
        0,
        0,
        0,
        0,
        0,
        -31325.202131785016,
        0,
        0,
        0,
        0,
        0,
        0,
        0,
        0,
        0,
        -1000000,
        158033.5944856056,
        0,
        -1000000,
        0,
        0,
        624415.5823228466,
        -47209.28353602548,
        0,
        -823924.979739328,
        -45126.41768301606,
        0,
        0,
        0,
        0,
        0,
        0,
        -1000000,
        0,
        -375278.8522719493,
        0,
        0,
        0,
        0,
        0,
        0,
        1000000,
        0,
        0,
        0
    ],
    "curvatures": [
        0,
        0,
        0,
        0,
        0,
        1,
        1,
        0,
        0.25,
        0.35355339059327373,
        0,
        0.042669245863479165,
        0.17677669529663687,
        0.15811388300841897,
        0.072,
        0.04754198431127886,
        0.014036676682383634,
        0.000549820080885262,
        0.00025298221281347036,
        0.0012276067819555886,
        0.0022316508420138007,
        0.0008245586020157391,
        0.0009023117515851417,
        0.00023907051845969716,
        0.0015005622372491131,
        0.00021551443937379953,
        0.0013766978626022432,
        0.0008481007493279211,
        0.0028495827396702628,
        0.0017034885262672639,
        0,
        0.011180339887498949,
        0.001603303386248364,
        0,
        0.03841972514007969,
        0.17677669529663687,
        0.044721359549995794,
        0.07133400736362736,
        0.021334622931739582,
        0.08944271909999159,
        0,
        0,
        4,
        0.17888543819998318,
        0.021334622931739582,
        0.022097086912079608,
        0.0038091161436245385,
        0.016,
        0,
        0.039283710065919304,
        0.08533849172695833,
        0.5,
        0.08838834764831843,
        1,
        2,
        0.17888543819998318,
        0.25,
        0.35355339059327373,
        1,
        0.35355339059327373,
        1,
        2,
        0.08944271909999159,
        0,
        2,
        0.2683281572999747,
        0.08944271909999159,
        0,
        0,
        0,
        0,
        0,
        0,
        0.35355339059327373,
        2,
        0.2683281572999747,
        0.2683281572999747,
        0.08944271909999159,
        0.35355339059327373,
        0.17888543819998318,
        0,
        0
    ],
    "pausePoints": [],
    "hesitation": 0,
    "hesitationLevel": "moderate",
    "totalTime": 1.444,
    "averageSpeed": 538.5231530528939,
    "deceptionFlag": false,
    "jerkSpikeCount": 11,
    "label": 1
}