{
    "question": "Are you currently located in Norway?",
    "answer": "Yes",
    "mouseMovements": [
        [
            712,
            420
        ],
        [
            711,
            420
        ],
        [
            710,
            420
        ],
        [
            710,
            419
        ],
        [
            709,
            419
        ],
        [
            709,
            417
        ],
        [
            709,
            416
        ],
        [
            709,
            414
        ],
        [
            710,
            412
        ],
        [
            711,
            409
        ],
        [
            712,
            406
        ],
        [
            714,
            400
        ],
        [
            716,
            392
        ],
        [
            716,
            384
        ],
        [
            719,
            371
        ],
        [
            721,
            357
        ],
        [
            724,
            342
        ],
        [
            728,
            324
        ],
        [
            728,
            304
        ],
        [
            728,
            285
        ],
        [
            730,
            271
        ],
        [
            734,
            248
        ],
        [
            736,
            240
        ],
        [
            738,
            233
        ],
        [
            741,
            226
        ],
        [
            743,
            220
        ],
        [
            744,
            218
        ],
        [
            746,
            216
        ],
        [
            747,
            216
        ],
        [
            744,
            216
        ],
        [
            741,
            217
        ],
        [
            740,
            217
        ],
        [
            738,
            218
        ],
        [
            737,
            219
        ],
        [
            735,
            219
        ],
        [
            732,
            220
        ],
        [
            728,
            222
        ],
        [
            723,
            224
        ],
        [
            716,
            226
        ],
        [
            710,
            227
        ],
        [
            704,
            230
        ],
        [
            699,
            231
        ],
        [
            696,
            232
        ],
        [
            693,
            234
        ],
        [
            691,
            235
        ],
        [
            689,
            237
        ],
        [
            688,
            237
        ],
        [
            688,
            238
        ],
        [
            688,
            239
        ],
        [
            687,
            239
        ],
        [
            686,
            239
        ],
        [
            686,
            241
        ],
        [
            685,
            243
        ],
        [
            684,
            243
        ],
        [
            684,
            245
        ],
        [
            682,
            247
        ],
        [
            681,
            249
        ],
        [
            680,
            251
        ],
        [
            679,
            254
        ],
        [
            677,
            257
        ],
        [
            676,
            260
        ],
        [
            676,
            263
        ],
        [
            676,
            265
        ],
        [
            676,
            267
        ],
        [
            676,
            265
        ],
        [
            677,
            264
        ],
        [
            677,
            263
        ],
        [
            678,
            263
        ],
        [
            678,
            262
        ],
        [
            678,
            261
        ],
        [
            678,
            260
        ],
        [
            679,
            259
        ],
        [
            680,
            259
        ],
        [
            680,
            258
        ],
        [
            680,
            257
        ],
        [
            680,
            256
        ],
        [
            681,
            255
        ]
    ],
    "timestamps": [
        0.013,
        0.071,
        0.149,
        0.372,
        0.41,
        0.431,
        0.438,
        0.445,
        0.452,
        0.459,
        0.466,
        0.473,
        0.479,
        0.486,
        0.494,
        0.503,
        0.51,
        0.516,
        0.524,
        0.532,
        0.54,
        0.556,
        0.565,
        0.572,
        0.579,
        0.586,
        0.593,
        0.602,
        0.61,
        0.767,
        0.775,
        0.783,
        0.789,
        0.797,
        0.804,
        0.82,
        0.827,
        0.834,
        0.84,
        0.847,
        0.854,
        0.861,
        0.868,
        0.875,
        0.882,
        0.892,
        0.899,
        0.907,
        0.914,
        0.924,
        0.93,
        0.937,
        0.944,
        0.951,
        0.965,
        0.972,
        0.979,
        0.986,
        0.993,
        1,
        1.007,
        1.014,
        1.035,
        1.042,
        1.237,
        1.244,
        1.264,
        1.271,
        1.294,
        1.313,
        1.32,
        1.33,
        1.347,
        1.355,
        1.364,
        1.368,
        1.389
    ],
    "accelerations": [
        0,
        -1096050.5283496627,
        -56.67777551066673,
        -37.382098151468135,
        574.5127510775997,
        3282.0145602100483,
        6802.721088435376,
        20408.163265306124,
        4817.7138265263175,
        18902.238421807957,
        0,
        64536.27877894652,
        78476.77316121705,
        -33073.05700220152,
        65606.35814483112,
        -10706.622819891032,
        87706.52494532542,
        147981.23475170752,
        -71647.68572053697,
        -15625,
        -75904.1308792039,
        -19293.110107829674,
        -60314.610739932396,
        17681.429126706153,
        6850.269726191625,
        -26351.38337810508,
        -83438.51720075446,
        -574.2891080683801,
        -23658.710065919317,
        -674.4695525173435,
        47022.05340828379,
        -33785.58844013093,
        41279.66604166083,
        -24487.66261916601,
        15562.512916806976,
        -5504.495747110125,
        63033.45874848802,
        18633.24188030458,
        74007.06500855794,
        -49197.93892236159,
        12764.110249003059,
        -32840.49834503235,
        -39525.34394743683,
        9046.40031215529,
        -27948.63873396325,
        -3659.557002535092,
        -19997.93851678231,
        -2232.142857142858,
        2551.020408163266,
        -4285.714285714286,
        11111.11111111111,
        17006.80272108844,
        4817.7138265263175,
        -25225.87709183244,
        0,
        37314.83928053449,
        -12088.962188702055,
        0,
        18902.238421807957,
        9046.40031215529,
        -9046.40031215529,
        -3311.788983028155,
        -15873.015873015871,
        27210.884353741498,
        -1412.6044895275663,
        27396.299807718846,
        -7601.525445522108,
        13265.30612244898,
        -4320.820955981637,
        481.75358304227404,
        12889.36627282492,
        -143.5786619833351,
        -4858.695695620283,
        8272.058823529413,
        -1543.2098765432097,
        34722.22222222222,
        -8697.928429992982
    ],
    "jerks": [
        0,
        -1000000,
        1000000,
        -1000000,
        -1000000,
        17433.528968037073,
        0,
        0,
        0,
        0,
        0,
        0,
        0,
        0,
        0,
        0,
        0,
        0,
        0,
        0,
        0,
        1000000,
        0,
        0,
        0,
        0,
        0,
        0,
        0,
        -21833.03449615004,
        0,
        0,
        0,
        0,
        0,
        -553125.4855474413,
        0,
        0,
        0,
        0,
        0,
        0,
        0,
        0,
        0,
        1000000,
        0,
        0,
        0,
        -854221.4221032313,
        0,
        0,
        0,
        0,
        1000000,
        0,
        0,
        0,
        0,
        0,
        0,
        0,
        -70686.2967134691,
        0,
        -131064.1825728155,
        0,
        -799901.8125558089,
        0,
        -264369.18436012865,
        251421.0148409744,
        0,
        -1000000,
        131517.0609734841,
        0,
        0,
        0,
        -1000000
    ],
    "curvatures": [
        0,
        0,
        0,
        1,
        1,
        2,
        0,
        0,
        0.25,
        0.08944271909999159,
        0,
        0,
        0.015811388300841896,
        0.02853360294545094,
        0.046875,
        0.006737363496592013,
        0.004242640687119285,
        0.001676206283232342,
        0.012760615165803303,
        0,
        0.00554016620498615,
        0.0035355339059327377,
        0.001100356168127279,
        0.0035667003681813677,
        0.018141961276241948,
        0.009055616059291212,
        0.007905694150420948,
        0.17888543819998318,
        0.08838834764831843,
        0,
        0.1111111111111111,
        0.03162277660168379,
        1,
        0.08944271909999159,
        0.7071067811865475,
        0.25,
        0.06324555320336758,
        0.022360679774997897,
        0.025613150093386463,
        0.012958543768744248,
        0.05331859047741318,
        0.029814239699997195,
        0.01508585654909108,
        0.09486832980505139,
        0.021334622931739582,
        0.17888543819998318,
        0.08838834764831843,
        1,
        0,
        1,
        0,
        2,
        0.25,
        0.17888543819998318,
        2,
        0.5,
        0.08838834764831843,
        0,
        0.08944271909999159,
        0.09486832980505139,
        0.06400386879521874,
        0.09486832980505139,
        0,
        0,
        0,
        0.25,
        0.35355339059327373,
        1,
        1,
        0,
        0,
        1,
        0.35355339059327373,
        1,
        0,
        0,
        1
    ],
    "pausePoints": [
        {
            "x": 710,
            "y": 419,
            "duration": 0.301
        },
        {
            "x": 709,
            "y": 419,
            "duration": 0.339
        }
    ],
    "hesitation": 0.64,
    "hesitationLevel": "moderate",
    "totalTime": 1.87,
    "averageSpeed": 238.30943912154046,
    "deceptionFlag": false,
    "jerkSpikeCount": 11,
    "label": 0
}